llama_index/llms/upstage/__init__.py
llama_index/llms/upstage/base.py
llama_index/llms/upstage/utils.py
llama_index_llms_upstage-0.6.5.dist-info/METADATA
llama_index_llms_upstage-0.6.5.dist-info/WHEEL
llama_index_llms_upstage-0.6.5.dist-info/licenses/LICENSE
llama_index_llms_upstage-0.6.5.dist-info/RECORD
