Metadata-Version: 2.4
Name: llama-index-llms-upstage
Version: 0.6.5
Summary: llama-index llms upstage integration
Author-email: Your Name <you@example.com>
License-Expression: AGPL-3.0
License-File: LICENSE
Requires-Python: <4.0,>=3.9
Requires-Dist: llama-index-core<0.15,>=0.14.3
Requires-Dist: llama-index-llms-openai<0.7,>=0.6.0
Requires-Dist: llama-index-readers-upstage<0.5,>=0.4.0
Requires-Dist: tokenizers<0.20,>=0.19.1
